velesresearch/__init__.py
velesresearch/helperModels.py
velesresearch/models.py
velesresearch/utils.py
velesresearch/validators.py
velesresearch/website_template/.gitignore
velesresearch/website_template/__init__.py
velesresearch/website_template/build.ts
velesresearch/website_template/bun.lockb
velesresearch/website_template/package.json
velesresearch/website_template/public/index.html
velesresearch/website_template/public/reload.js
velesresearch/website_template/recaptchaKeys.json
velesresearch/website_template/server.ts
velesresearch/website_template/src/SurveyComponent.jsx
velesresearch/website_template/src/csrf.ts
velesresearch/website_template/src/customExpressionFunctions.js
velesresearch/website_template/src/index.css
velesresearch/website_template/src/index.tsx
velesresearch/website_template/src/theme.json
velesresearch/website_template/tsconfig.json
velesresearch/wrappers.py
velesresearch-0.5.1.1.dist-info/LICENSE
velesresearch-0.5.1.1.dist-info/METADATA
velesresearch-0.5.1.1.dist-info/WHEEL
velesresearch-0.5.1.1.dist-info/RECORD
