Metadata-Version: 2.3
Name: velesresearch
Version: 0.5.1.1
Summary: Veles is a free and open source python survey tool for researchers.
License: GPL-3.0-or-later
Author: Jakub Jędrusiak
Author-email: kuba23031999@gmail.com
Requires-Python: >=3.11,<4.0
Classifier: License :: OSI Approved :: GNU General Public License v3 or later (GPLv3+)
Classifier: Programming Language :: Python :: 3
Classifier: Programming Language :: Python :: 3.11
Classifier: Programming Language :: Python :: 3.12
Classifier: Programming Language :: Python :: 3.13
Requires-Dist: markdown (>=3.4.3,<4.0.0)
Requires-Dist: pydantic (>=2.0.0,<3.0.0)
Project-URL: Documentation, https://docs.velesweb.org/
Project-URL: Repository, https://github.com/jakub-jedrusiak/VelesResearch
